<?xml version="1.0" encoding="utf-8"?>
<!DOCTYPE hibernate-mapping PUBLIC "-//Hibernate/Hibernate Mapping DTD 3.0//EN"
"http://hibernate.sourceforge.net/hibernate-mapping-3.0.dtd">
<!-- 
    Mapping file autogenerated by MyEclipse Persistence Tools
-->
<hibernate-mapping>
    <class name="com.rdfs.framework.workflow.entity.CwTaskNode" table="cw_task_node" >
        <id name="id" type="java.lang.Integer">
            <column name="id"/>
            <generator class="identity"></generator>
        </id>
        <property name="name" type="java.lang.String">
            <column name="name"></column>
        </property>
        <property name="code" type="java.lang.String">
            <column name="code"></column>
        </property>
        <property name="type" type="java.lang.String">
            <column name="type"></column>
        </property>
        <many-to-one name="processInfo" class="com.rdfs.framework.workflow.entity.CwProcessInfo" not-found="ignore">
        	<column name="process_id"></column>
        </many-to-one>
        <bag name="nodeEvents" lazy="true" cascade="all-delete-orphan" inverse="true">
            <key>
                <column name="curr_node" not-null="true"/>
            </key>
            <one-to-many class="com.rdfs.framework.workflow.entity.CwNodeEvent" />
        </bag>
    </class>
</hibernate-mapping>
